ether_real_estate/__init__.py
ether_real_estate/bank.py
ether_real_estate/building.py
ether_real_estate/contract.py
ether_real_estate/firm.py
ether_real_estate/game.py
ether_real_estate/player.py
etherealestate/__init__.py
etherealestate/bank.py
etherealestate/building.py
etherealestate/contract.py
etherealestate/firm.py
etherealestate/game.py
etherealestate/player.py
ether_real_estate-1.1.dist-info/LICENSE
ether_real_estate-1.1.dist-info/METADATA
ether_real_estate-1.1.dist-info/WHEEL
ether_real_estate-1.1.dist-info/top_level.txt
ether_real_estate-1.1.dist-info/RECORD
